include/patchwork/patchworkpp.h
lib/cmake/patchworkpp/patchworkppConfig-release.cmake
lib/cmake/patchworkpp/patchworkppConfig.cmake
lib/cmake/patchworkpp/patchworkppTargets-release.cmake
lib/cmake/patchworkpp/patchworkppTargets.cmake
lib/ground_seg_cores.lib
pypatchworkpp.cp311-win_amd64.pyd
pypatchworkpp-1.0.4.dist-info/METADATA
pypatchworkpp-1.0.4.dist-info/WHEEL
pypatchworkpp-1.0.4.dist-info/RECORD
